gpa_calculator_bd/__init__.py
gpa_calculator_bd/average.py
gpa_calculator_bd/cgpa.py
gpa_calculator_bd/gpa.py
gpa_calculator_bd-0.2.dist-info/LICENSE
gpa_calculator_bd-0.2.dist-info/METADATA
gpa_calculator_bd-0.2.dist-info/WHEEL
gpa_calculator_bd-0.2.dist-info/top_level.txt
gpa_calculator_bd-0.2.dist-info/RECORD
